pymarket/__init__.py
pymarket/conftest.py
pymarket/market.py
pymarket/bids/__init__.py
pymarket/bids/bids.py
pymarket/bids/demand_curves.py
pymarket/bids/processing.py
pymarket/datasets/__init__.py
pymarket/datasets/uniform_bidders.py
pymarket/mechanisms/__init__.py
pymarket/mechanisms/huang_auction.py
pymarket/mechanisms/mechanism.py
pymarket/mechanisms/muda_auction.py
pymarket/mechanisms/p2p_random.py
pymarket/plot/__init__.py
pymarket/plot/demand_curves.py
pymarket/plot/huang.py
pymarket/plot/muda.py
pymarket/plot/trades.py
pymarket/statistics/__init__.py
pymarket/statistics/maximum_aggregated_utility.py
pymarket/statistics/maximum_traded_volume.py
pymarket/statistics/profits.py
pymarket/statistics/statistics.py
pymarket/transactions/__init__.py
pymarket/transactions/processing.py
pymarket/transactions/transactions.py
pymarket/utils/__init__.py
pymarket/utils/decorators.py
pymarket-0.7.5.dist-info/AUTHORS.rst
pymarket-0.7.5.dist-info/LICENSE
pymarket-0.7.5.dist-info/METADATA
pymarket-0.7.5.dist-info/WHEEL
pymarket-0.7.5.dist-info/top_level.txt
pymarket-0.7.5.dist-info/RECORD
