Metadata-Version: 2.1
Name: pymarket
Version: 0.7.5
Summary: A simple library for simulating markets in Python
Home-page: https://github.com/gus0k/pymarket
Author: Diego Kiedanki
Author-email: gusok@protonmail.com
License: MIT license
Keywords: pymarket
Platform: UNKNOWN
Classifier: Development Status :: 2 - Pre-Alpha
Classifier: Intended Audience :: Developers
Classifier: License :: OSI Approved :: MIT License
Classifier: Natural Language :: English
Classifier: Programming Language :: Python :: 3.6
Classifier: Programming Language :: Python :: 3.7
Requires-Dist: Click (>=6.0)
Requires-Dist: pandas (>=0.24)
Requires-Dist: numpy (>=1.16)
Requires-Dist: networkx
Requires-Dist: pulp
Requires-Dist: matplotlib
